{
	"id": "84eda62b-0cbd-4c34-a7f7-861d0e84fd85",
	"name": "Norsk Gjeldsinformasjon - Public Environment",
	"values": [
		{
			"key": "auth_server_base_uri",
			"value": "https://access-preprod.norskgjeld.no",
			"enabled": true
		},
		{
			"key": "api_base_uri",
			"value": "https://api-preprod.norskgjeld.no",
			"enabled": true
		},
		{
			"key": "api_audience",
			"value": "https://api-preprod.norskgjeld.no/v1/debt",
			"enabled": true
		},
		{
			"key": "authorization_code",
			"value": "Not set. Received on the callback at the end of the authorization code flow",
			"enabled": true
		},
		{
			"key": "client_id",
			"value": "Not set",
			"enabled": true
		},
		{
			"key": "client_secret",
			"value": "Not set",
			"enabled": true
		},
		{
			"key": "client_redirect",
			"value": "Not set",
			"enabled": true
		},
		{
			"key": "authorization_flow_access_token",
			"value": "Will be set by scripts while running the requests",
			"enabled": true
		},
		{
			"key": "client_credentials_access_token",
			"value": "Will be set by scripts while running the requests",
			"enabled": true
		},
		{
			"key": "consent_id",
			"value": "Will be set by scripts while running the requests",
			"enabled": true
		}
	],
	"_postman_variable_scope": "environment",
	"_postman_exported_at": "2021-02-24T11:30:26.981Z",
	"_postman_exported_using": "Postman/8.0.6"
}